experiments/__init__.py
experiments/exceptions.py
experiments/experiment.py
experiments/protocols.py
experiments/py.typed
experiments/tracker.py
experiments/types.py
experiments-2.0.0.dist-info/METADATA
experiments-2.0.0.dist-info/WHEEL
experiments-2.0.0.dist-info/RECORD
