Metadata-Version: 2.4
Name: experiments
Version: 2.0.0
Summary: A collection of code for experiments.
Project-URL: Homepage, https://github.com/gao-hongnan/experiments
Project-URL: Issues, https://github.com/gao-hongnan/experiments/issues
Author-email: GAO Hongnan <hongnangao@gmail.com>
Classifier: License :: OSI Approved :: Apache Software License
Classifier: Operating System :: OS Independent
Classifier: Programming Language :: Python :: 3
Classifier: Programming Language :: Python :: 3.12
Classifier: Programming Language :: Python :: 3.13
Requires-Python: >=3.12
Requires-Dist: pydantic-settings>=2.10.1
Requires-Dist: pydantic>=2.11.7
Requires-Dist: rich>=13.0.0
Provides-Extra: experiments
Requires-Dist: aioboto3>=15.0.0; extra == 'experiments'
Requires-Dist: boto3-stubs[s3]>=1.34.0; extra == 'experiments'
Requires-Dist: boto3>=1.34.0; extra == 'experiments'
Requires-Dist: botocore>=1.34.0; extra == 'experiments'
Requires-Dist: duckdb==1.3.2; extra == 'experiments'
Requires-Dist: mypy-boto3-s3>=1.39.5; extra == 'experiments'
Requires-Dist: numpy>=2.3.2; extra == 'experiments'
Requires-Dist: types-aioboto3>=15.0.0; extra == 'experiments'
Requires-Dist: types-aiobotocore-s3>=2.23.1; extra == 'experiments'
